pytest_circleci_parallelized.py
pytest_circleci_parallelized_rjp-0.1.0.dist-info/LICENSE
pytest_circleci_parallelized_rjp-0.1.0.dist-info/METADATA
pytest_circleci_parallelized_rjp-0.1.0.dist-info/WHEEL
pytest_circleci_parallelized_rjp-0.1.0.dist-info/entry_points.txt
pytest_circleci_parallelized_rjp-0.1.0.dist-info/top_level.txt
pytest_circleci_parallelized_rjp-0.1.0.dist-info/RECORD
