Metadata-Version: 2.1
Name: pytest-circleci-parallelized-rjp
Version: 0.1.0
Summary: Parallelize pytest across CircleCI workers.
Home-page: https://github.com/RJPercival/pytest-circleci-parallelized
Author: Ryan Wilson-Perkin
Author-email: ryanwilsonperkin@gmail.com
Maintainer: Rob Percival
Maintainer-email: rob.percival87@gmail.com
License: MIT
Classifier: Framework :: Pytest
Classifier: Intended Audience :: Developers
Classifier: Topic :: Software Development :: Testing
Classifier: Programming Language :: Python
Classifier: Programming Language :: Python :: 3
Classifier: Programming Language :: Python :: 3.7
Classifier: Operating System :: OS Independent
Classifier: License :: OSI Approved :: MIT License
Requires-Python: >=3.7
License-File: LICENSE
Requires-Dist: pytest
